eikeskog_github_tools/github_tools.py
eikeskog_github_tools-0.0.5.dist-info/METADATA
eikeskog_github_tools-0.0.5.dist-info/WHEEL
eikeskog_github_tools-0.0.5.dist-info/top_level.txt
eikeskog_github_tools-0.0.5.dist-info/RECORD
