Metadata-Version: 2.1
Name: eikeskog-github-tools
Version: 0.0.5
Summary: Use github api to perform tasks, e.g. check pr status, create milestone..
Author-email: Svein Tore Eikeskog <st@eikeskog.com>
Requires-Dist: requests
